<?xml version="1.0" encoding="UTF-8"?>
<!DOCTYPE mapper PUBLIC "-//mybatis.org//DTD Mapper 3.0//EN"
        "http://mybatis.org/dtd/mybatis-3-mapper.dtd">
<mapper namespace="com.dashboard.mapper.RequirementMapper">

    <resultMap id="requirementMap" type="com.dashboard.entity.Requirement">
        <id property="id" column="id"/>
        <result property="functionName" column="function_name"/>
        <result property="moduleName" column="module_name"/>
        <result property="requestDepartment" column="request_department"/>
        <result property="requestOwner" column="request_owner"/>
        <result property="productOwner" column="product_owner"/>
        <result property="priority" column="priority"/>
        <result property="plannedStartTime" column="planned_start_time"/>
        <result property="plannedEndTime" column="planned_end_time"/>
        <result property="actualStartTime" column="actual_start_time"/>
        <result property="actualEndTime" column="actual_end_time"/>
        <result property="status" column="status"/>
        <result property="description" column="description"/>
        <result property="createdAt" column="created_at"/>
        <result property="updatedAt" column="updated_at"/>
    </resultMap>

    <select id="findList" resultMap="requirementMap">
        SELECT * FROM requirement
        <where>
            <if test="functionName != null and functionName != ''">
                AND function_name LIKE CONCAT('%', #{functionName}, '%')
            </if>
            <if test="requestDepartment != null and requestDepartment != ''">
                AND request_department LIKE CONCAT('%', #{requestDepartment}, '%')
            </if>
            <if test="productOwner != null and productOwner != ''">
                AND product_owner LIKE CONCAT('%', #{productOwner}, '%')
            </if>
            <if test="priority != null and priority.size() > 0">
                AND priority IN
                <foreach collection="priority" item="p" open="(" separator="," close=")">
                    #{p}
                </foreach>
            </if>
            <if test="status != null and status.size() > 0">
                AND status IN
                <foreach collection="status" item="s" open="(" separator="," close=")">
                    #{s}
                </foreach>
            </if>
        </where>
        <choose>
            <when test="sortField == 'plannedStartTime' and sortOrder == 'ascending'">ORDER BY planned_start_time ASC</when>
            <when test="sortField == 'plannedStartTime' and sortOrder == 'descending'">ORDER BY planned_start_time DESC</when>
            <when test="sortField == 'plannedEndTime' and sortOrder == 'ascending'">ORDER BY planned_end_time ASC</when>
            <when test="sortField == 'plannedEndTime' and sortOrder == 'descending'">ORDER BY planned_end_time DESC</when>
            <when test="sortField == 'actualStartTime' and sortOrder == 'ascending'">ORDER BY actual_start_time ASC</when>
            <when test="sortField == 'actualStartTime' and sortOrder == 'descending'">ORDER BY actual_start_time DESC</when>
            <when test="sortField == 'actualEndTime' and sortOrder == 'ascending'">ORDER BY actual_end_time ASC</when>
            <when test="sortField == 'actualEndTime' and sortOrder == 'descending'">ORDER BY actual_end_time DESC</when>
            <when test="sortField == 'priority' and sortOrder == 'ascending'">ORDER BY CASE priority WHEN '紧急' THEN 1 WHEN '高' THEN 2 WHEN '中' THEN 3 WHEN '低' THEN 4 ELSE 5 END ASC</when>
            <when test="sortField == 'priority' and sortOrder == 'descending'">ORDER BY CASE priority WHEN '紧急' THEN 1 WHEN '高' THEN 2 WHEN '中' THEN 3 WHEN '低' THEN 4 ELSE 5 END DESC</when>
            <otherwise>ORDER BY CASE priority WHEN '紧急' THEN 1 WHEN '高' THEN 2 WHEN '中' THEN 3 WHEN '低' THEN 4 ELSE 5 END ASC</otherwise>
        </choose>
    </select>

    <select id="findById" resultMap="requirementMap">
        SELECT * FROM requirement WHERE id = #{id}
    </select>

    <insert id="insert" parameterType="com.dashboard.entity.Requirement" useGeneratedKeys="true" keyProperty="id">
        INSERT INTO requirement (function_name, module_name, request_department, request_owner,
                                 product_owner, priority, planned_start_time, planned_end_time,
                                 actual_start_time, actual_end_time, status, description)
        VALUES (#{functionName}, #{moduleName}, #{requestDepartment}, #{requestOwner},
                #{productOwner}, #{priority}, #{plannedStartTime}, #{plannedEndTime},
                #{actualStartTime}, #{actualEndTime}, #{status}, #{description})
    </insert>

    <update id="update" parameterType="com.dashboard.entity.Requirement">
        UPDATE requirement
        <set>
            <if test="functionName != null">function_name = #{functionName},</if>
            <if test="moduleName != null">module_name = #{moduleName},</if>
            <if test="requestDepartment != null">request_department = #{requestDepartment},</if>
            <if test="requestOwner != null">request_owner = #{requestOwner},</if>
            <if test="productOwner != null">product_owner = #{productOwner},</if>
            <if test="priority != null">priority = #{priority},</if>
            <if test="plannedStartTime != null">planned_start_time = #{plannedStartTime},</if>
            <if test="plannedEndTime != null">planned_end_time = #{plannedEndTime},</if>
            <if test="actualStartTime != null">actual_start_time = #{actualStartTime},</if>
            <if test="actualEndTime != null">actual_end_time = #{actualEndTime},</if>
            <if test="status != null">status = #{status},</if>
            <if test="description != null">description = #{description},</if>
        </set>
        WHERE id = #{id}
    </update>

    <delete id="deleteById">
        DELETE FROM requirement WHERE id = #{id}
    </delete>

    <select id="statsByDepartment" resultType="map">
        SELECT request_department AS name, COUNT(*) AS value
        FROM requirement
        WHERE request_department IS NOT NULL AND request_department != ''
        GROUP BY request_department
    </select>

    <select id="statsByPriority" resultType="map">
        SELECT priority AS name, COUNT(*) AS value
        FROM requirement
        WHERE priority IS NOT NULL AND priority != ''
        <if test="department != null and department != ''">
            AND request_department = #{department}
        </if>
        GROUP BY priority
    </select>

    <select id="statsByStatus" resultType="map">
        SELECT status AS name, COUNT(*) AS value
        FROM requirement
        <if test="department != null and department != ''">
            WHERE request_department = #{department}
        </if>
        GROUP BY status
    </select>

</mapper>
